{
  "kind": "Config",
  "apiVersion": "v1",
  "clusters": [
    {
      "name": "default",
      "cluster": {
        "server": "https://host.docker.internal:16443",
        "insecure-skip-tls-verify": true
      }
    }
  ],
  "users": [
    {
      "name": "default",
      "user": {
        "client-certificate-data": "<base64-client-certificate-data>",
        "client-key-data": "<base64-client-key-data>"
      }
    }
  ],
  "contexts": [
    {
      "name": "default",
      "context": {
        "cluster": "default",
        "user": "default",
        "namespace": "ppanel-dev"
      }
    }
  ],
  "current-context": "default"
}
